MANIFEST.in
README.rst
setup.py
aiolirc/__init__.pxd
aiolirc/__init__.py
aiolirc/c_lirc_client.pxd
aiolirc/compat.py
aiolirc/dispatcher.py
aiolirc/exceptions.py
aiolirc/lirc_client.c
aiolirc/lirc_client.pyx
aiolirc.egg-info/PKG-INFO
aiolirc.egg-info/SOURCES.txt
aiolirc.egg-info/dependency_links.txt
aiolirc.egg-info/not-zip-safe
aiolirc.egg-info/requires.txt
aiolirc.egg-info/top_level.txt
aiolirc/tests/__init__.py
aiolirc/tests/helpers.py
aiolirc/tests/test_dispatcher.py
aiolirc/tests/test_lirc_client.py