Metadata-Version: 1.1
Name: aiolirc
Version: 0.1.2
Summary: lirc python extension for asyncio
Home-page: http://aiolirc.dobisel.com
Author: Vahid Mardani
Author-email: vahid.mardani@gmail.com
License: GPLv3
Keywords: lirc asyncio extension
Platform: UNKNOWN
Classifier: Programming Language :: Python :: 3.5
Classifier: Programming Language :: Python :: 3.6
Classifier: Programming Language :: Python :: Implementation :: CPython
Classifier: Programming Language :: Cython
Classifier: Development Status :: 4 - Beta
Classifier: License :: OSI Approved :: GNU General Public License v3 (GPLv3)
Classifier: Environment :: Console
Classifier: Intended Audience :: Developers
Classifier: Natural Language :: English
Classifier: Operating System :: Unix
Classifier: Topic :: Software Development :: Libraries :: Python Modules
Classifier: Topic :: System :: Hardware
